<?xml version="1.0" encoding="UTF-8"?>
<configuration>
    <include resource="org/springframework/boot/logging/logback/defaults.xml"/>
    
    <!-- 定义日志文件路径（可通过环境变量或系统属性覆盖） -->
    <!-- Windows 默认使用项目目录下的 logs 文件夹，Linux 使用 /var/log/app -->
    <!-- 优先使用 application.yaml 中的 logging.file.path，否则使用默认值 -->
    <springProperty scope="context" name="LOG_HOME" source="logging.file.path" defaultValue="logs"/>
    <property name="LOG_FILE_NAME" value="${LOG_FILE_NAME:-application}"/>
    
    <!-- 控制台输出 -->
    <appender name="CONSOLE" class="ch.qos.logback.core.ConsoleAppender">
        <encoder>
            <pattern>%d{yyyy-MM-dd HH:mm:ss.SSS} [%thread] %-5level %logger{50} - %msg%n</pattern>
            <charset>UTF-8</charset>
        </encoder>
    </appender>
    
    <!-- 文件输出 - 所有日志 -->
    <appender name="FILE" class="ch.qos.logback.core.rolling.RollingFileAppender">
        <file>${LOG_HOME}/${LOG_FILE_NAME}.log</file>
        <encoder>
            <pattern>%d{yyyy-MM-dd HH:mm:ss.SSS} [%thread] %-5level %logger{50} - %msg%n</pattern>
            <charset>UTF-8</charset>
        </encoder>
        <rollingPolicy class="ch.qos.logback.core.rolling.TimeBasedRollingPolicy">
            <fileNamePattern>${LOG_HOME}/${LOG_FILE_NAME}-%d{yyyy-MM-dd}.log</fileNamePattern>
            <maxHistory>30</maxHistory>
            <totalSizeCap>10GB</totalSizeCap>
        </rollingPolicy>
    </appender>
    
    <!-- 文件输出 - 错误日志 -->
    <appender name="ERROR_FILE" class="ch.qos.logback.core.rolling.RollingFileAppender">
        <file>${LOG_HOME}/${LOG_FILE_NAME}-error.log</file>
        <filter class="ch.qos.logback.classic.filter.LevelFilter">
            <level>ERROR</level>
            <onMatch>ACCEPT</onMatch>
            <onMismatch>DENY</onMismatch>
        </filter>
        <encoder>
            <pattern>%d{yyyy-MM-dd HH:mm:ss.SSS} [%thread] %-5level %logger{50} - %msg%n</pattern>
            <charset>UTF-8</charset>
        </encoder>
        <rollingPolicy class="ch.qos.logback.core.rolling.TimeBasedRollingPolicy">
            <fileNamePattern>${LOG_HOME}/${LOG_FILE_NAME}-error-%d{yyyy-MM-dd}.log</fileNamePattern>
            <maxHistory>90</maxHistory>
            <totalSizeCap>5GB</totalSizeCap>
        </rollingPolicy>
    </appender>
    
    <!-- JSON 格式输出（用于 Logstash 解析） -->
    <appender name="JSON_FILE" class="ch.qos.logback.core.rolling.RollingFileAppender">
        <file>${LOG_HOME}/${LOG_FILE_NAME}-json.log</file>
        <encoder class="net.logstash.logback.encoder.LoggingEventCompositeJsonEncoder">
            <providers>
                <timestamp>
                    <timeZone>Asia/Shanghai</timeZone>
                </timestamp>
                <version/>
                <logLevel/>
                <loggerName/>
                <message/>
                <mdc/>
                <stackTrace/>
                <pattern>
                    <pattern>
                        {
                            "thread": "%thread",
                            "class": "%logger{40}",
                            "method": "%method",
                            "line": "%line"
                        }
                    </pattern>
                </pattern>
            </providers>
        </encoder>
        <rollingPolicy class="ch.qos.logback.core.rolling.TimeBasedRollingPolicy">
            <fileNamePattern>${LOG_HOME}/${LOG_FILE_NAME}-json-%d{yyyy-MM-dd}.log</fileNamePattern>
            <maxHistory>30</maxHistory>
            <totalSizeCap>10GB</totalSizeCap>
        </rollingPolicy>
    </appender>
    
    <!-- Spring Boot 日志 -->
    <logger name="org.springframework" level="INFO"/>
    <logger name="org.apache" level="INFO"/>
    <logger name="org.apache.shardingsphere" level="INFO"/>
    
    <!-- 应用日志 -->
    <logger name="org.lix.mycatdemo" level="DEBUG"/>
    
    <!-- 根日志级别 -->
    <root level="INFO">
        <appender-ref ref="CONSOLE"/>
        <appender-ref ref="FILE"/>
        <appender-ref ref="ERROR_FILE"/>
        <appender-ref ref="JSON_FILE"/>
    </root>
</configuration>

